heaviside/__init__.py
heaviside/__main__.py
heaviside/activities.py
heaviside/ast.py
heaviside/aws_services.json
heaviside/exceptions.py
heaviside/lexer.py
heaviside/parser.py
heaviside/sfn.py
heaviside/utils.py
heaviside/tests/__init__.py
heaviside/tests/test_activities.py
heaviside/tests/test_compile.py
heaviside/tests/test_statemachine.py
heaviside/tests/test_utils.py
heaviside/tests/utils.py
heaviside-2.2.5.dist-info/LICENSE
heaviside-2.2.5.dist-info/METADATA
heaviside-2.2.5.dist-info/WHEEL
heaviside-2.2.5.dist-info/entry_points.txt
heaviside-2.2.5.dist-info/top_level.txt
heaviside-2.2.5.dist-info/RECORD
