Metadata-Version: 2.1
Name: heaviside
Version: 2.2.5
Summary: Python library and DSL for working with AWS StepFunctions
Author: Derek Pryor
License: Apache License
Project-URL: Homepage, https://github.com/jhuapl-boss/heaviside
Project-URL: Issues, https://github.com/jhuapl-boss/heaviside/issues
Project-URL: Changelog, https://github.com/jhuapl-boss/heaviside/blob/master/CHANGELOG.md
Keywords: bossdb,microns,aws,stepfunctions,dsl
Classifier: Development Status :: 5 - Production/Stable
Classifier: Intended Audience :: Developers
Classifier: License :: OSI Approved :: Apache Software License
Classifier: Programming Language :: Python :: 3
Requires-Python: >=3.8
License-File: LICENSE
Requires-Dist: hvac <1.0.0,>=0.11.2
Requires-Dist: setuptools >=75.3.0
Requires-Dist: funcparserlib ==1.0.1
Requires-Dist: iso8601
Requires-Dist: boto3 >=1.4.3
Requires-Dist: importlib-resources
